llama_index/llms/helicone/__init__.py
llama_index/llms/helicone/base.py
llama_index/llms/helicone/py.typed
llama_index_llms_helicone-0.1.1.dist-info/METADATA
llama_index_llms_helicone-0.1.1.dist-info/WHEEL
llama_index_llms_helicone-0.1.1.dist-info/licenses/LICENSE
llama_index_llms_helicone-0.1.1.dist-info/RECORD
