Metadata-Version: 2.4
Name: llama-index-llms-helicone
Version: 0.1.1
Summary: llama-index llms helicone (OpenAI-compatible) integration
Author-email: Hammad Shami <hammad@helicone.ai>
License-Expression: MIT
License-File: LICENSE
Requires-Python: <4.0,>=3.9
Requires-Dist: llama-index-core<0.15,>=0.13.0
Requires-Dist: llama-index-llms-openai-like<0.6,>=0.5.0
